<?xml version="1.0" encoding="utf-8" ?>
<dwsync>
<file name=".DS_Store" server="droto.net" local="130503678392971702" remote="130503717000000000" Dst="2" />
<file name="config.json" server="droto.net" local="130503678393061760" remote="130503717000000000" Dst="2" />
<file name="DanielRotondoResume.doc" server="droto.net" local="130503678393011738" remote="130503717000000000" Dst="2" />
<file name="DanielRotondoResume.pdf" server="droto.net" local="130503678393051751" remote="130503717000000000" Dst="2" />
<file name="favicon.ico" server="droto.net" local="130503678393209434" remote="130503717000000000" Dst="2" />
<file name="favicon.png" server="droto.net" local="130503678393219452" remote="130503717000000000" Dst="2" />
<file name="holder.js" server="droto.net" local="130503678394320181" remote="130503717000000000" Dst="2" />
<file name="index.html" server="droto.net" local="130503678394350203" remote="130503717000000000" Dst="2" />
</dwsync>